goblintools/__init__.py
goblintools/config.py
goblintools/file_handling.py
goblintools/ocr_parser.py
goblintools/parser.py
goblintools/text_cleaner.py
goblintools-0.6.0.dist-info/licenses/LICENSE
goblintools-0.6.0.dist-info/METADATA
goblintools-0.6.0.dist-info/WHEEL
goblintools-0.6.0.dist-info/top_level.txt
goblintools-0.6.0.dist-info/RECORD
