Metadata-Version: 2.4
Name: goblintools
Version: 0.6.0
Summary: Toolkit for archive extraction, OCR parsing, and file text extraction
Author: Gean Matos
Author-email: Gean Matos <gean@webgoal.com.br>
License: MIT
Project-URL: Homepage, https://github.com/geanatelie/goblintools.git
Project-URL: Repository, https://github.com/geanatelie/goblintools.git
Requires-Python: >=3.7
License-File: LICENSE
Requires-Dist: patool
Requires-Dist: rarfile
Requires-Dist: boto3
Requires-Dist: opencv-python-headless
Requires-Dist: numpy
Requires-Dist: pdf2image
Requires-Dist: pypdf
Requires-Dist: beautifulsoup4
Requires-Dist: striprtf
Requires-Dist: dbfread
Requires-Dist: python-docx
Requires-Dist: python-pptx
Requires-Dist: openpyxl
Requires-Dist: xlrd
Requires-Dist: odfpy
Requires-Dist: unidecode
Requires-Dist: pytesseract
Requires-Dist: scipy
Requires-Dist: pillow
Dynamic: author
Dynamic: license-file
